usda_api/__init__.py
usda_api/scrapers/__init__.py
usda_api/scrapers/esr/__init__.py
usda_api/scrapers/esr/main.py
usda_api/scrapers/esr/schemas/__init__.py
usda_api/scrapers/esr/schemas/response.py
usda_api/scrapers/gats/__init__.py
usda_api/scrapers/psd/__init__.py
usda_api-0.1.2.dist-info/METADATA
usda_api-0.1.2.dist-info/WHEEL
usda_api-0.1.2.dist-info/entry_points.txt
usda_api-0.1.2.dist-info/top_level.txt
usda_api-0.1.2.dist-info/RECORD
