Metadata-Version: 2.1
Name: usda-api
Version: 0.1.2
Author: Loh YI Kuang
License: Apache License 2.0
Requires-Python: >=3.9
Requires-Dist: mypy-extensions (>=0.4.3)
Requires-Dist: mixpanel (>=4.9.0)
Requires-Dist: pandas (==2.0.0)
Requires-Dist: pydantic (>=1.5.1)
Requires-Dist: typing-inspect
Requires-Dist: typing-extensions (>=3.7.4.3) ; python_version < "3.8"
Requires-Dist: typing-extensions (>=3.10.0.2) ; python_version >= "3.8"
Provides-Extra: dev
Requires-Dist: pytest (>=6.2.2) ; extra == 'dev'
Requires-Dist: coverage (>=5.1) ; extra == 'dev'
Requires-Dist: black (==22.10.0) ; extra == 'dev'
Requires-Dist: pip-chill (==1.0.1) ; extra == 'dev'
Requires-Dist: flake8-tidy-imports (>=4.3.0) ; extra == 'dev'
Requires-Dist: pytest-testmon (==1.4.2) ; extra == 'dev'
Requires-Dist: vulture (==2.7) ; extra == 'dev'
Requires-Dist: pre-commit (==2.20.0) ; extra == 'dev'
Requires-Dist: flake8 (>=3.8.3) ; extra == 'dev'
Requires-Dist: isort (>=5.7.0) ; extra == 'dev'
Requires-Dist: mypy (==0.991) ; extra == 'dev'
Requires-Dist: pytest-asyncio (==0.20.3) ; extra == 'dev'
